brevesky/__init__.py
brevesky/cli.py
brevesky-0.1.4.dist-info/licenses/LICENSE
brevesky-0.1.4.dist-info/METADATA
brevesky-0.1.4.dist-info/WHEEL
brevesky-0.1.4.dist-info/entry_points.txt
brevesky-0.1.4.dist-info/top_level.txt
brevesky-0.1.4.dist-info/RECORD
