Metadata-Version: 2.4
Name: brevesky
Version: 0.1.4
Summary: Comando para borrar tus publicaciones/interacciones de BlueSky
License-Expression: AGPL-3.0-only
Project-URL: Repository, https://github.com/beigna/brevesky
Keywords: cli,bluesky
Requires-Python: >=3.10
License-File: LICENSE
Requires-Dist: python-dotenv==1.1.1
Requires-Dist: click==8.2.1
Requires-Dist: atproto==0.0.61
Dynamic: license-file
